[
  {
    "icon": "pe-7s-mouse",
    "title": "Sustainable Innovation",
    "solidColor": "#dbffeb",
    "color": "green",
    "details": "Harness the power of solar energy with our state-of-the-art solutions that support clean energy production and environmental sustainability"
  },
  {
    "icon": "pe-7s-airplay",
    "title": "Robust Legal Structure",
    "solidColor": "#ffdbdb",
    "color": "red",
    "details": "We help you build a solid legal foundation for your crypto ventures"
  },
  {
    "icon": "pe-7s-news-paper",
    "title": "legally team and technologically advanced",
    "solidColor": "#dbdeff",
    "color": "blue",
    "details": "Proven Expertise with a track record of success, we navigate the complexities of cryptocurrency and blockchain projects"
  }
]